setup.py
paylib/__init__.py
paylib/simple.py
paylib/static.py
paylib.egg-info/PKG-INFO
paylib.egg-info/SOURCES.txt
paylib.egg-info/dependency_links.txt
paylib.egg-info/not-zip-safe
paylib.egg-info/top_level.txt
paylib/paypal/__init__.py
paylib/paypal/core.py
paylib/paypal/fields.py
paylib/paypal/util.py
paylib/paypal/requests/__init__.py
paylib/paypal/requests/createrecurringpaymentsprofile.py
paylib/paypal/requests/doexpresscheckoutpayment.py
paylib/paypal/requests/getbalance.py
paylib/paypal/requests/getexpresscheckoutdetails.py
paylib/paypal/requests/managerecurringpaymentsprofilestatus.py
paylib/paypal/requests/setexpresscheckout.py