Metadata-Version: 1.0
Name: paylib
Version: 0.2.1
Summary: Simple PayPal Express Checkout API abstraction for python
Home-page: https://github.com/rutherford/PayLib
Author: Matt Rutherford
Author-email: rutherford@clientsideweb.net
License: MIT
Platform: UNKNOWN
